jrfapp/__init__.py
jrfapp/inv_pso_thickness.py
jrfapp/inverse_routine.py
jrfapp/main_classes.py
jrfapp/main_inv_all.py
jrfapp/rftan_classes.py
jrfapp/utils.py
jrfapp-0.0.59.dist-info/LICENSE
jrfapp-0.0.59.dist-info/METADATA
jrfapp-0.0.59.dist-info/WHEEL
jrfapp-0.0.59.dist-info/top_level.txt
jrfapp-0.0.59.dist-info/RECORD
