Metadata-Version: 2.1
Name: jrfapp
Version: 0.0.59
Summary: Joint inversion of Receiver function and Apparant velocity
Author-email: Mohammad Veisi <m.veisi9687@gmail.com>
License: MIT License
Project-URL: Homepage, https://github.com/mveisi/jrfapp
Classifier: Development Status :: 3 - Alpha
Classifier: Operating System :: POSIX :: Linux
Classifier: License :: OSI Approved :: MIT License
Classifier: Programming Language :: Python :: 3
Requires-Python: >=3.5
License-File: LICENSE
Requires-Dist: numpy
Requires-Dist: scipy
Requires-Dist: obspy
Requires-Dist: rf
Requires-Dist: matplotlib
